ocpymemcache/__init__.py
ocpymemcache/client.py
ocpymemcache/hash_client.py
ocpymemcache/observability.py
ocpymemcache-0.0.4.dist-info/METADATA
ocpymemcache-0.0.4.dist-info/RECORD
ocpymemcache-0.0.4.dist-info/WHEEL
ocpymemcache-0.0.4.dist-info/namespace_packages.txt
ocpymemcache-0.0.4.dist-info/top_level.txt
